
    {
            "puzzlePieces" : {  "f2":"wB", "g2":"wN", "a7":"wB", "f7":"wN", "g7":"wR", "b8":"wB", "d8":"wB", "g8":"wQ" }      ,
            "puzzleSolution" : {  "f2":"wB", "g2":"wN", "a7":"wB", "f7":"wN", "g7":"wR", "b8":"wB", "d8":"wB", "g8":"wQ" }    ,
            "puzzleNumbers" : {  "e1":2, "g1":1, "h2":1, "e3":3, "g3":3, "d4":2, "f4":2, "g4":1, "h4":3, "a5":1, "c5":2, "e5":2, "g5":3, "b6":3, "d6":2, "f6":1, "g6":1, "h6":1, "c7":2, "e7":1, "h7":2, "e8":1, "f8":1, "h8":2 }     ,
            "sparePieces" : false,
            "strictSolution" : false
    }