
    {
            "puzzlePieces" : {  "h5":"wK", "b6":"bR", "g6":"wR", "a7":"wB", "g7":"wR", "h7":"wR", "c8":"wN", "e8":"wB" }      ,
            "puzzleSolution" : {  "h5":"wK", "b6":"bR", "g6":"wR", "a7":"wB", "g7":"wR", "h7":"wR", "c8":"wN", "e8":"wB" }    ,
            "puzzleNumbers" : {  "b1":-1, "g1":1, "b2":-1, "g2":1, "b3":-1, "g3":1, "a4":1, "b4":-1, "g4":2, "h4":1, "g5":2, "a6":-1, "c6":1, "d6":1, "h6":3, "c7":1, "d7":2, "e7":2, "f7":2, "g8":1, "h8":1 }     ,
            "sparePieces" : false,
            "strictSolution" : false
    }