
    {
            "puzzlePieces" : {  "h4":"wN", "g6":"wB", "h6":"wR", "d7":"wB", "h7":"wB", "e8":"wB", "h8":"wK" }      ,
            "puzzleSolution" : {  "h4":"wN", "g6":"wB", "h6":"wR", "d7":"wB", "h7":"wB", "e8":"wB", "h8":"wK" }    ,
            "puzzleNumbers" : {  "b1":1, "c2":1, "g2":1, "d3":1, "f3":1, "h3":1, "a4":1, "e4":1, "g4":1, "b5":1, "f5":3, "h5":2, "c6":1, "e6":1, "f7":2, "g7":1, "c8":1, "g8":2 }     ,
            "sparePieces" : false,
            "strictSolution" : false
    }