
    {
            "puzzlePieces" : {  "d1":"wN", "e1":"wR", "g1":"wR", "h1":"wQ", "e4":"wP", "g4":"wP", "h4":"wB" }      ,
            "puzzleSolution" : {  "d1":"wN", "e1":"wR", "g1":"wR", "h1":"wQ", "e4":"wP", "g4":"wP", "h4":"wB" }    ,
            "puzzleNumbers" : {  "f1":2, "b2":1, "e2":1, "f2":2, "g2":2, "h2":1, "c3":1, "e3":2, "f3":1, "g3":2, "h3":1, "d5":1, "f5":2, "g5":1, "h5":1, "f6":1, "e7":1, "d8":1 }     ,
            "sparePieces" : false,
            "strictSolution" : false
    }